README.md
setup.py
zubr/__init__.py
zubr_temp.egg-info/PKG-INFO
zubr_temp.egg-info/SOURCES.txt
zubr_temp.egg-info/dependency_links.txt
zubr_temp.egg-info/requires.txt
zubr_temp.egg-info/top_level.txt