Metadata-Version: 2.1
Name: zubr-temp
Version: 0.2.4
Summary: Zubr exchange SDK
Home-page: http://github.com/zubr/sdk
Author: Zubr Exchange Developers
Author-email: developer@zubr.io
License: MIT
Platform: UNKNOWN
Classifier: Programming Language :: Python :: 3
Classifier: License :: OSI Approved :: MIT License
Classifier: Operating System :: OS Independent
Requires-Python: >=3.6
